pyThermoCalcDB/__init__.py
pyThermoCalcDB/app.py
pyThermoCalcDB/configs/__init__.py
pyThermoCalcDB/configs/constants.py
pyThermoCalcDB/configs/info.py
pyThermoCalcDB/configs/thermo_props.py
pyThermoCalcDB/core/__init__.py
pyThermoCalcDB/core/calc.py
pyThermoCalcDB/core/calc_sat.py
pyThermoCalcDB/core/component_vapor.py
pyThermoCalcDB/core/hsg_mixture.py
pyThermoCalcDB/core/hsg_properties.py
pyThermoCalcDB/core/hsg_reaction.py
pyThermoCalcDB/docs/__init__.py
pyThermoCalcDB/docs/main.py
pyThermoCalcDB/docs/sat.py
pyThermoCalcDB/docs/thermo.py
pyThermoCalcDB/models/__init__.py
pyThermoCalcDB/models/component_ref.py
pyThermoCalcDB/models/density.py
pyThermoCalcDB/models/enthalpy.py
pyThermoCalcDB/models/heat_capacity.py
pyThermoCalcDB/models/ref.py
pyThermoCalcDB/models/vapor_pressure.py
pyThermoCalcDB/reactions/reactions.py
pyThermoCalcDB/reactions/rxn.py
pyThermoCalcDB/reactions/source.py
pyThermoCalcDB/thermo/__init__.py
pyThermoCalcDB/thermo/density.py
pyThermoCalcDB/thermo/enthalpy.py
pyThermoCalcDB/thermo/entropy.py
pyThermoCalcDB/thermo/gibbs.py
pyThermoCalcDB/thermo/heat_capacity.py
pyThermoCalcDB/thermo/vapor_pressure.py
pyThermoCalcDB/utils/__init__.py
pyThermoCalcDB/utils/component_tools.py
pyThermoCalcDB/utils/conversions.py
pyThermoCalcDB/utils/math_tools.py
pyThermoCalcDB/utils/tools.py
pythermocalcdb-0.7.7.dist-info/licenses/LICENSE
pythermocalcdb-0.7.7.dist-info/METADATA
pythermocalcdb-0.7.7.dist-info/WHEEL
pythermocalcdb-0.7.7.dist-info/top_level.txt
pythermocalcdb-0.7.7.dist-info/RECORD
