Metadata-Version: 2.4
Name: pyThermoCalcDB
Version: 0.7.7
Summary: Python Thermodynamic Calculation Engine powered by PyThermoDB.
Author-email: Sina Gilassi <sina.gilassi@gmail.com>
License-Expression: Apache-2.0
Project-URL: Homepage, https://github.com/sinagilassi/pyThermoCalcDB
Project-URL: Source, https://github.com/sinagilassi/pyThermoCalcDB
Project-URL: Tracker, https://github.com/sinagilassi/pyThermoCalcDB/issues
Keywords: chemical-engineering,thermodynamics,thermodynamic-equations,thermodynamic-properties,process-simulation
Classifier: Development Status :: 1 - Planning
Classifier: Intended Audience :: Education
Classifier: Programming Language :: Python :: 3.11
Classifier: Operating System :: Unix
Classifier: Operating System :: MacOS :: MacOS X
Classifier: Operating System :: Microsoft :: Windows
Requires-Python: >=3.11
License-File: LICENSE
Requires-Dist: scipy>=1.16.0
Requires-Dist: pydantic>=2.12.5
Requires-Dist: pydantic-settings>=2.12.0
Requires-Dist: rich>=14.2.0
Requires-Dist: pycuc>=2.4.0
Requires-Dist: pythermodb>=1.12.2
Requires-Dist: pythermolinkdb>=1.4.9
Requires-Dist: pythermodb-settings>=0.2.3
Requires-Dist: pyreactlab-core>=0.1.3
Dynamic: license-file
